auto_token-0.0.10.dist-info/METADATA
auto_token-0.0.10.dist-info/WHEEL
auto_token-0.0.10.dist-info/entry_points.txt
auto_token/__init__.py
auto_token/__main__.py
auto_token/__version__.py
auto_token/model/__init__.py
auto_token/model/config.py
auto_token/model/token.py
auto_token/utils.py
auto_token-0.0.10.dist-info/RECORD
