Metadata-Version: 2.1
Name: auto-token
Version: 0.0.10
Summary: auto manage token
Author-Email: Zhan Rongrui <2742392377@qq.com>
License: MIT
Requires-Python: >=3.10
Requires-Dist: loguru>=0.7.2
Requires-Dist: rich>=13.7.0
Requires-Dist: typer>=0.12.0
Requires-Dist: cachetools>=5.3.2
Requires-Dist: toml>=0.10.2
Requires-Dist: pydantic>=2.6.1
Provides-Extra: watch
Requires-Dist: watchfiles; extra == "watch"
Provides-Extra: all
Requires-Dist: auto-token[watch]; extra == "all"
